ckanext_csvtocsvw-1.0.3-py3.13-nspkg.pth
ckanext/csvtocsvw/__init__.py
ckanext/csvtocsvw/action.py
ckanext/csvtocsvw/annotate.py
ckanext/csvtocsvw/auth.py
ckanext/csvtocsvw/cli.py
ckanext/csvtocsvw/csvw_parser.py
ckanext/csvtocsvw/helpers.py
ckanext/csvtocsvw/plugin.py
ckanext/csvtocsvw/tasks.py
ckanext/csvtocsvw/views.py
ckanext/csvtocsvw/assets/script.js
ckanext/csvtocsvw/assets/style.css
ckanext/csvtocsvw/assets/webassets.yml
ckanext/csvtocsvw/i18n/de/LC_MESSAGES/ckanext-csvtocsvw.mo
ckanext/csvtocsvw/templates/csvtocsvw/csv_annotate.html
ckanext/csvtocsvw/templates/csvtocsvw/csv_transform.html
ckanext/csvtocsvw/templates/package/resource_read.html
ckanext/csvtocsvw/templates/package/snippets/resource_item.html
ckanext/csvtocsvw/tests/__init__.py
ckanext_csvtocsvw-1.0.3.dist-info/licenses/LICENSE
ckanext_csvtocsvw-1.0.3.dist-info/METADATA
ckanext_csvtocsvw-1.0.3.dist-info/WHEEL
ckanext_csvtocsvw-1.0.3.dist-info/entry_points.txt
ckanext_csvtocsvw-1.0.3.dist-info/namespace_packages.txt
ckanext_csvtocsvw-1.0.3.dist-info/top_level.txt
ckanext_csvtocsvw-1.0.3.dist-info/RECORD
