Metadata-Version: 2.4
Name: ckanext-csvtocsvw
Version: 1.0.3
Summary: Extension automatically generating csvw metadata for uploaded textual tabular data.
Home-page: https://github.com/Mat-O-Lab/ckanext-csvtocsvw
Author: Thomas Hanke
Author-email: thomas.hanke@iwm.fraunhofer.de
License: AGPL
Keywords: CKAN CSVW CSV JSON-LD
Classifier: Development Status :: 4 - Beta
Classifier: License :: OSI Approved :: GNU Affero General Public License v3 or later (AGPLv3+)
Classifier: Programming Language :: Python :: 3.7
Classifier: Programming Language :: Python :: 3.8
Classifier: Programming Language :: Python :: 3.9
Classifier: Programming Language :: Python :: 3.10
License-File: LICENSE
Requires-Dist: ckanapi
Requires-Dist: requests>=2.4.2
Requires-Dist: requests_toolbelt
Requires-Dist: pytest
Requires-Dist: pytest-ckan
Requires-Dist: rdflib
Requires-Dist: pandas
Requires-Dist: ckan
Dynamic: author
Dynamic: author-email
Dynamic: description
Dynamic: description-content-type
Dynamic: home-page
Dynamic: license
Dynamic: license-file
Dynamic: requires-dist
Dynamic: summary
